xbox/__init__.py
xbox/client.py
xbox/decorators.py
xbox/exceptions.py
xbox/proxies.py
xbox/resource.py
xbox/utils.py
xbox/tests/__init__.py
xbox/tests/conftest.py
xbox/tests/test_authentication.py
xbox/tests/test_clips.py
xbox/tests/test_decorators.py
xbox/tests/test_gamer_profile.py
xbox/tests/test_serialisation.py
xbox/tests/test_utils.py
xbox/vendor/__init__.py
xbox/vendor/six.py
xbox/vendor/requests/__init__.py
xbox/vendor/requests/adapters.py
xbox/vendor/requests/api.py
xbox/vendor/requests/auth.py
xbox/vendor/requests/cacert.pem
xbox/vendor/requests/certs.py
xbox/vendor/requests/compat.py
xbox/vendor/requests/cookies.py
xbox/vendor/requests/exceptions.py
xbox/vendor/requests/hooks.py
xbox/vendor/requests/models.py
xbox/vendor/requests/sessions.py
xbox/vendor/requests/status_codes.py
xbox/vendor/requests/structures.py
xbox/vendor/requests/utils.py
xbox/vendor/requests/packages/__init__.py
xbox/vendor/requests/packages/chardet/__init__.py
xbox/vendor/requests/packages/chardet/big5freq.py
xbox/vendor/requests/packages/chardet/big5prober.py
xbox/vendor/requests/packages/chardet/chardetect.py
xbox/vendor/requests/packages/chardet/chardistribution.py
xbox/vendor/requests/packages/chardet/charsetgroupprober.py
xbox/vendor/requests/packages/chardet/charsetprober.py
xbox/vendor/requests/packages/chardet/codingstatemachine.py
xbox/vendor/requests/packages/chardet/compat.py
xbox/vendor/requests/packages/chardet/constants.py
xbox/vendor/requests/packages/chardet/cp949prober.py
xbox/vendor/requests/packages/chardet/escprober.py
xbox/vendor/requests/packages/chardet/escsm.py
xbox/vendor/requests/packages/chardet/eucjpprober.py
xbox/vendor/requests/packages/chardet/euckrfreq.py
xbox/vendor/requests/packages/chardet/euckrprober.py
xbox/vendor/requests/packages/chardet/euctwfreq.py
xbox/vendor/requests/packages/chardet/euctwprober.py
xbox/vendor/requests/packages/chardet/gb2312freq.py
xbox-0.1.3.dist-info/DESCRIPTION.rst
xbox-0.1.3.dist-info/METADATA
xbox-0.1.3.dist-info/metadata.json
xbox-0.1.3.dist-info/RECORD
xbox-0.1.3.dist-info/top_level.txt
xbox-0.1.3.dist-info/WHEEL
