Metadata-Version: 2.0
Name: xbox
Version: 0.1.3
Summary: A wrapper around Microsoft's undocumented Xbox One APIs
Home-page: https://github.com/buttscicles/xbox/
Author: Joe Alcorn
Author-email: joealcorn123@gmail.com
License: MIT
Keywords: xbox one microsoft
Platform: UNKNOWN
Classifier: Intended Audience :: Developers
Classifier: License :: OSI Approved :: MIT License
Classifier: Programming Language :: Python
Classifier: Programming Language :: Python :: 2
Classifier: Programming Language :: Python :: 2.6
Classifier: Programming Language :: Python :: 2.7
Classifier: Programming Language :: Python :: 3
Classifier: Programming Language :: Python :: 3.1
Classifier: Programming Language :: Python :: 3.2
Classifier: Programming Language :: Python :: 3.3
Classifier: Programming Language :: Python :: 3.4
Classifier: Programming Language :: Python :: Implementation :: PyPy
